{"cameraMode":{"drawMode":0,"name":"Shaded","section":"Shading Mode"},"sceneLighting":true,"audioPlay":false,"sceneViewState":{"m_AlwaysRefresh":false,"showFog":true,"showSkybox":true,"showFlares":true,"showImageEffects":true,"showParticleSystems":true,"showVisualEffectGraphs":true,"m_FxEnabled":true},"in2DMode":false,"pivot":{"x":466.7093505859375,"y":-11.312335968017579,"z":548.141845703125},"rotation":{"x":-0.2320832461118698,"y":0.42754316329956057,"z":-0.11452146619558335,"w":-0.8661907315254211},"size":12.413161277770996,"orthographic":false}